macro_correct/__init__.py
macro_correct/predict_csc_punct_zh.py
macro_correct/predict_csc_token_zh.py
macro_correct/version.py
macro_correct/corpus/__init__.py
macro_correct/corpus/sequence_labeling/__init__.py
macro_correct/corpus/sequence_labeling/chinese_symbol/__init__.py
macro_correct/corpus/text_correction/__init__.py
macro_correct/corpus/text_correction/espell/__init__.py
macro_correct/corpus/text_correction/public/__init__.py
macro_correct/corpus/text_correction/sighan/__init__.py
macro_correct/corpus/text_correction/wang271k/__init__.py
macro_correct/output/__init__.py
macro_correct/output/confusion_dict.json
macro_correct/output/csc.config
macro_correct/output/idx2pun.json
macro_correct/output/sequence_labeling/__init__.py
macro_correct/output/text_correction/__init__.py
macro_correct/pytorch_sequencelabeling/__init__.py
macro_correct/pytorch_sequencelabeling/slAdversarial.py
macro_correct/pytorch_sequencelabeling/slConfig.py
macro_correct/pytorch_sequencelabeling/slData.py
macro_correct/pytorch_sequencelabeling/slGraph.py
macro_correct/pytorch_sequencelabeling/slLayer.py
macro_correct/pytorch_sequencelabeling/slOffice.py
macro_correct/pytorch_sequencelabeling/slPredict.py
macro_correct/pytorch_sequencelabeling/slRun.py
macro_correct/pytorch_sequencelabeling/slTools.py
macro_correct/pytorch_sequencelabeling/slTqdm.py
macro_correct/pytorch_textcorrection/__init__.py
macro_correct/pytorch_textcorrection/tcAdversarial.py
macro_correct/pytorch_textcorrection/tcConfig.py
macro_correct/pytorch_textcorrection/tcData.py
macro_correct/pytorch_textcorrection/tcEval.py
macro_correct/pytorch_textcorrection/tcGraph.py
macro_correct/pytorch_textcorrection/tcLayer.py
macro_correct/pytorch_textcorrection/tcOffice.py
macro_correct/pytorch_textcorrection/tcPredict.py
macro_correct/pytorch_textcorrection/tcRun.py
macro_correct/pytorch_textcorrection/tcTools.py
macro_correct/pytorch_textcorrection/tcTqdm.py
macro_correct/pytorch_textcorrection/tcTrie.py
macro_correct-0.0.5.dist-info/LICENSE
macro_correct-0.0.5.dist-info/METADATA
macro_correct-0.0.5.dist-info/WHEEL
macro_correct-0.0.5.dist-info/top_level.txt
macro_correct-0.0.5.dist-info/RECORD
