Metadata-Version: 2.1
Name: macro-correct
Version: 0.0.5
Summary: macro-correct
Home-page: https://github.com/yongzhuo/macro-correct
Author: yongzhuo
Author-email: 1903865025@qq.com
License: Apache
Requires-Dist: huggingface-hub (>=0.25.1)
Requires-Dist: transformers (>=4.30.2)
Requires-Dist: numpy (>=1.18.1)
Requires-Dist: torch (>=1.10.0)
Requires-Dist: opencc (>=1.1.1)
